LICENSE
MANIFEST.in
README.rst
requirements.txt
setup.py
tox.ini
docs/Makefile
docs/conf.py
docs/index.rst
docs/make.bat
docs/modules.rst
docs/sdeint.rst
sdeint/__init__.py
sdeint/integrate.py
sdeint/wiener.py
sdeint.egg-info/PKG-INFO
sdeint.egg-info/SOURCES.txt
sdeint.egg-info/dependency_links.txt
sdeint.egg-info/not-zip-safe
sdeint.egg-info/requires.txt
sdeint.egg-info/top_level.txt
sdeint/tests/plot_results.py
sdeint/tests/test_integrate.py
sdeint/tests/test_wiener.py