Metadata-Version: 2.1
Name: sdeint
Version: 0.3.0
Summary: Numerical integration of stochastic differential equations (SDE)
Home-page: http://github.com/mattja/sdeint/
Author: Matthew J. Aburn
Author-email: mattja6@gmail.com
License: GPLv3+
Keywords: stochastic,differential equations,SDE,SODE
Platform: any
Classifier: Programming Language :: Python
Classifier: Development Status :: 3 - Alpha
Classifier: Intended Audience :: Science/Research
Classifier: License :: OSI Approved :: GNU General Public License (GPL)
Classifier: Operating System :: OS Independent
Classifier: Topic :: Scientific/Engineering
Provides-Extra: implicit_algorithms
License-File: LICENSE
